clear_lambda_storage.py
clear_lambda_storage-1.0.1.dist-info/LICENSE
clear_lambda_storage-1.0.1.dist-info/METADATA
clear_lambda_storage-1.0.1.dist-info/WHEEL
clear_lambda_storage-1.0.1.dist-info/entry_points.txt
clear_lambda_storage-1.0.1.dist-info/top_level.txt
clear_lambda_storage-1.0.1.dist-info/RECORD
