Metadata-Version: 2.1
Name: clear-lambda-storage
Version: 1.0.1
Summary: Clear Lambda code storage
Home-page: https://github.com/epsagon/clear-lambda-storage
Author: 
Author-email: 
License: UNKNOWN
Platform: UNKNOWN
Classifier: Programming Language :: Python :: 3
Classifier: License :: OSI Approved :: MIT License
Classifier: Operating System :: OS Independent
Requires-Python: >=3
Requires-Dist: boto3
